<?xml version='1.0' encoding='UTF-8' standalone='yes' ?>
<hierarchy index="0" class="hierarchy" rotation="0" width="2160" height="3840">
  <android.widget.FrameLayout index="0" package="com.udates" class="android.widget.FrameLayout" text="" checkable="false" checked="false" clickable="false" enabled="true" focusable="false" focused="false" long-clickable="false" password="false" scrollable="false" selected="false" bounds="[0,0][2160,3840]" displayed="true">
    <android.widget.LinearLayout index="0" package="com.udates" class="android.widget.LinearLayout" text="" checkable="false" checked="false" clickable="false" enabled="true" focusable="false" focused="false" long-clickable="false" password="false" scrollable="false" selected="false" bounds="[0,0][2160,3840]" displayed="true">
      <android.widget.FrameLayout index="0" package="com.udates" class="android.widget.FrameLayout" text="" checkable="false" checked="false" clickable="false" enabled="true" focusable="false" focused="false" long-clickable="false" password="false" scrollable="false" selected="false" bounds="[0,122][2160,3840]" displayed="true">
        <android.widget.LinearLayout index="0" package="com.udates" class="android.widget.LinearLayout" text="" resource-id="com.udates:id/action_bar_root" checkable="false" checked="false" clickable="false" enabled="true" focusable="false" focused="false" long-clickable="false" password="false" scrollable="false" selected="false" bounds="[0,122][2160,3840]" displayed="true">
          <android.widget.FrameLayout index="0" package="com.udates" class="android.widget.FrameLayout" text="" resource-id="android:id/content" checkable="false" checked="false" clickable="false" enabled="true" focusable="false" focused="false" long-clickable="false" password="false" scrollable="false" selected="false" bounds="[0,122][2160,3840]" displayed="true">
            <android.widget.ImageView index="0" package="com.udates" class="android.widget.ImageView" text="" checkable="false" checked="false" clickable="false" enabled="true" focusable="false" focused="false" long-clickable="false" password="false" scrollable="false" selected="false" bounds="[0,122][2160,3840]" displayed="true" />
            <android.widget.FrameLayout index="1" package="com.udates" class="android.widget.FrameLayout" text="" checkable="false" checked="false" clickable="false" enabled="true" focusable="false" focused="false" long-clickable="false" password="false" scrollable="false" selected="false" bounds="[0,122][2160,3840]" displayed="true">
              <android.view.ViewGroup index="0" package="com.udates" class="android.view.ViewGroup" text="" checkable="false" checked="false" clickable="false" enabled="true" focusable="false" focused="false" long-clickable="false" password="false" scrollable="false" selected="false" bounds="[0,122][2160,3840]" displayed="true">
                <android.view.ViewGroup index="0" package="com.udates" class="android.view.ViewGroup" text="" checkable="false" checked="false" clickable="false" enabled="true" focusable="false" focused="false" long-clickable="false" password="false" scrollable="false" selected="false" bounds="[0,122][2160,3840]" displayed="true">
                  <android.view.ViewGroup index="0" package="com.udates" class="android.view.ViewGroup" text="" checkable="false" checked="false" clickable="false" enabled="true" focusable="false" focused="false" long-clickable="false" password="false" scrollable="false" selected="false" bounds="[0,122][2160,3840]" displayed="true">
                    <android.view.ViewGroup index="0" package="com.udates" class="android.view.ViewGroup" text="" checkable="false" checked="false" clickable="false" enabled="true" focusable="false" focused="false" long-clickable="false" password="false" scrollable="false" selected="false" bounds="[0,122][2160,3840]" displayed="true">
                      <android.view.ViewGroup index="0" package="com.udates" class="android.view.ViewGroup" text="" checkable="false" checked="false" clickable="false" enabled="true" focusable="false" focused="false" long-clickable="false" password="false" scrollable="false" selected="false" bounds="[0,122][2160,3840]" displayed="true">
                        <android.view.ViewGroup index="0" package="com.udates" class="android.view.ViewGroup" text="" checkable="false" checked="false" clickable="false" enabled="true" focusable="false" focused="false" long-clickable="false" password="false" scrollable="false" selected="false" bounds="[0,122][2160,3840]" displayed="true">
                          <android.view.ViewGroup index="0" package="com.udates" class="android.view.ViewGroup" text="" checkable="false" checked="false" clickable="false" enabled="true" focusable="false" focused="false" long-clickable="false" password="false" scrollable="false" selected="false" bounds="[0,122][2160,3840]" displayed="true">
                            <android.view.ViewGroup index="0" package="com.udates" class="android.view.ViewGroup" text="" checkable="false" checked="false" clickable="false" enabled="true" focusable="false" focused="false" long-clickable="false" password="false" scrollable="false" selected="false" bounds="[0,122][2160,3840]" displayed="true">
                              <android.widget.FrameLayout index="0" package="com.udates" class="android.widget.FrameLayout" text="" checkable="false" checked="false" clickable="false" enabled="true" focusable="false" focused="false" long-clickable="false" password="false" scrollable="false" selected="false" bounds="[0,122][2160,3840]" displayed="true">
                                <android.view.ViewGroup index="0" package="com.udates" class="android.view.ViewGroup" text="" checkable="false" checked="false" clickable="false" enabled="true" focusable="false" focused="false" long-clickable="false" password="false" scrollable="false" selected="false" bounds="[0,122][2160,3840]" displayed="true">
                                  <android.view.ViewGroup index="1" package="com.udates" class="android.view.ViewGroup" text="" checkable="false" checked="false" clickable="false" enabled="true" focusable="false" focused="false" long-clickable="false" password="false" scrollable="false" selected="false" bounds="[0,122][2160,3840]" displayed="true">
                                    <android.view.ViewGroup index="0" package="com.udates" class="android.view.ViewGroup" text="" checkable="false" checked="false" clickable="false" enabled="true" focusable="false" focused="false" long-clickable="false" password="false" scrollable="false" selected="false" bounds="[0,122][2160,3840]" displayed="true" />
                                    <android.view.ViewGroup index="1" package="com.udates" class="android.view.ViewGroup" text="" checkable="false" checked="false" clickable="false" enabled="true" focusable="false" focused="false" long-clickable="false" password="false" scrollable="false" selected="false" bounds="[0,122][2160,3840]" displayed="true">
                                      <android.view.ViewGroup index="0" package="com.udates" class="android.view.ViewGroup" text="" checkable="false" checked="false" clickable="false" enabled="true" focusable="false" focused="false" long-clickable="false" password="false" scrollable="false" selected="false" bounds="[0,122][2160,3840]" displayed="true">
                                        <android.view.ViewGroup index="0" package="com.udates" class="android.view.ViewGroup" text="" checkable="false" checked="false" clickable="false" enabled="true" focusable="false" focused="false" long-clickable="false" password="false" scrollable="false" selected="false" bounds="[0,122][2160,3840]" displayed="true">
                                          <android.view.ViewGroup index="0" package="com.udates" class="android.view.ViewGroup" text="" checkable="false" checked="false" clickable="false" enabled="true" focusable="false" focused="false" long-clickable="false" password="false" scrollable="false" selected="false" bounds="[0,122][2160,3840]" displayed="true">
                                            <android.view.ViewGroup index="1" package="com.udates" class="android.view.ViewGroup" text="" checkable="false" checked="false" clickable="false" enabled="true" focusable="false" focused="false" long-clickable="false" password="false" scrollable="false" selected="false" bounds="[0,122][2160,3840]" displayed="true">
                                              <android.view.ViewGroup index="0" package="com.udates" class="android.view.ViewGroup" text="" checkable="false" checked="false" clickable="false" enabled="true" focusable="false" focused="false" long-clickable="false" password="false" scrollable="false" selected="false" bounds="[0,122][2160,3840]" displayed="true">
                                                <android.view.ViewGroup index="0" package="com.udates" class="android.view.ViewGroup" text="" checkable="false" checked="false" clickable="false" enabled="true" focusable="false" focused="false" long-clickable="false" password="false" scrollable="false" selected="false" bounds="[0,122][2160,3590]" displayed="true">
                                                  <android.view.ViewGroup index="0" package="com.udates" class="android.view.ViewGroup" text="" checkable="false" checked="false" clickable="false" enabled="true" focusable="false" focused="false" long-clickable="false" password="false" scrollable="false" selected="false" bounds="[0,122][2160,3590]" displayed="true">
                                                    <android.view.ViewGroup index="0" package="com.udates" class="android.view.ViewGroup" text="" checkable="false" checked="false" clickable="false" enabled="true" focusable="false" focused="false" long-clickable="false" password="false" scrollable="false" selected="false" bounds="[0,122][2160,3590]" displayed="true">
                                                      <android.view.ViewGroup index="0" package="com.udates" class="android.view.ViewGroup" text="" checkable="false" checked="false" clickable="false" enabled="true" focusable="false" focused="false" long-clickable="false" password="false" scrollable="false" selected="false" bounds="[0,122][2160,3590]" displayed="true">
                                                        <android.view.ViewGroup index="0" package="com.udates" class="android.view.ViewGroup" text="" checkable="false" checked="false" clickable="false" enabled="true" focusable="false" focused="false" long-clickable="false" password="false" scrollable="false" selected="false" bounds="[0,122][2160,3590]" displayed="true">
                                                          <android.view.ViewGroup index="0" package="com.udates" class="android.view.ViewGroup" text="" checkable="false" checked="false" clickable="false" enabled="true" focusable="false" focused="false" long-clickable="false" password="false" scrollable="false" selected="false" bounds="[0,122][2160,3590]" displayed="true">
                                                            <android.view.ViewGroup index="0" package="com.udates" class="android.view.ViewGroup" text="" checkable="false" checked="false" clickable="false" enabled="true" focusable="false" focused="false" long-clickable="false" password="false" scrollable="false" selected="false" bounds="[0,122][2160,3590]" displayed="true">
                                                              <android.view.ViewGroup index="0" package="com.udates" class="android.view.ViewGroup" text="" checkable="false" checked="false" clickable="false" enabled="true" focusable="false" focused="false" long-clickable="false" password="false" scrollable="false" selected="false" bounds="[0,122][2160,3590]" displayed="true">
                                                                <android.view.ViewGroup index="0" package="com.udates" class="android.view.ViewGroup" text="" checkable="false" checked="false" clickable="false" enabled="true" focusable="false" focused="false" long-clickable="false" password="false" scrollable="false" selected="false" bounds="[0,122][2160,3590]" displayed="true">
                                                                  <android.widget.FrameLayout index="0" package="com.udates" class="android.widget.FrameLayout" text="" checkable="false" checked="false" clickable="false" enabled="true" focusable="false" focused="false" long-clickable="false" password="false" scrollable="false" selected="false" bounds="[0,122][2160,3590]" displayed="true">
                                                                    <android.view.ViewGroup index="0" package="com.udates" class="android.view.ViewGroup" text="" checkable="false" checked="false" clickable="false" enabled="true" focusable="false" focused="false" long-clickable="false" password="false" scrollable="false" selected="false" bounds="[0,122][2160,3590]" displayed="true">
                                                                      <android.view.ViewGroup index="1" package="com.udates" class="android.view.ViewGroup" text="" checkable="false" checked="false" clickable="false" enabled="true" focusable="false" focused="false" long-clickable="false" password="false" scrollable="false" selected="false" bounds="[0,122][2160,3590]" displayed="true">
                                                                        <android.view.ViewGroup index="0" package="com.udates" class="android.view.ViewGroup" text="" checkable="false" checked="false" clickable="false" enabled="true" focusable="false" focused="false" long-clickable="false" password="false" scrollable="false" selected="false" bounds="[0,122][2160,3590]" displayed="true" />
                                                                        <android.view.ViewGroup index="1" package="com.udates" class="android.view.ViewGroup" text="" checkable="false" checked="false" clickable="false" enabled="true" focusable="false" focused="false" long-clickable="false" password="false" scrollable="false" selected="false" bounds="[0,122][2160,3590]" displayed="true">
                                                                          <android.view.ViewGroup index="0" package="com.udates" class="android.view.ViewGroup" text="" checkable="false" checked="false" clickable="false" enabled="true" focusable="false" focused="false" long-clickable="false" password="false" scrollable="false" selected="false" bounds="[0,122][2160,3590]" displayed="true">
                                                                            <android.view.ViewGroup index="0" package="com.udates" class="android.view.ViewGroup" text="" checkable="false" checked="false" clickable="false" enabled="true" focusable="false" focused="false" long-clickable="false" password="false" scrollable="false" selected="false" bounds="[0,122][2160,3590]" displayed="true">
                                                                              <android.view.ViewGroup index="0" package="com.udates" class="android.view.ViewGroup" text="" checkable="false" checked="false" clickable="false" enabled="true" focusable="false" focused="false" long-clickable="false" password="false" scrollable="false" selected="false" bounds="[0,122][2160,3590]" displayed="true">
                                                                                <android.view.ViewGroup index="0" package="com.udates" class="android.view.ViewGroup" text="" checkable="false" checked="false" clickable="false" enabled="true" focusable="false" focused="false" long-clickable="false" password="false" scrollable="false" selected="false" bounds="[0,122][2160,408]" displayed="true">
                                                                                  <android.view.ViewGroup index="0" package="com.udates" class="android.view.ViewGroup" text="" checkable="false" checked="false" clickable="false" enabled="true" focusable="false" focused="false" long-clickable="false" password="false" scrollable="false" selected="false" bounds="[0,122][2160,408]" displayed="true">
                                                                                    <android.view.ViewGroup index="0" package="com.udates" class="android.view.ViewGroup" text="" checkable="false" checked="false" clickable="false" enabled="true" focusable="false" focused="false" long-clickable="false" password="false" scrollable="false" selected="false" bounds="[0,122][2160,408]" displayed="true">
                                                                                      <android.view.ViewGroup index="0" package="com.udates" class="android.view.ViewGroup" text="" checkable="false" checked="false" clickable="false" enabled="true" focusable="false" focused="false" long-clickable="false" password="false" scrollable="false" selected="false" bounds="[0,122][2160,408]" displayed="true" />
                                                                                    </android.view.ViewGroup>
                                                                                    <android.view.ViewGroup index="1" package="com.udates" class="android.view.ViewGroup" text="" checkable="false" checked="false" clickable="false" enabled="true" focusable="false" focused="false" long-clickable="false" password="false" scrollable="false" selected="false" bounds="[0,122][2160,408]" displayed="true">
                                                                                      <android.view.ViewGroup index="1" package="com.udates" class="android.view.ViewGroup" text="" checkable="false" checked="false" clickable="false" enabled="true" focusable="false" focused="false" long-clickable="false" password="false" scrollable="false" selected="false" bounds="[0,122][2160,408]" displayed="true">
                                                                                        <android.view.ViewGroup index="1" package="com.udates" class="android.view.ViewGroup" text="" checkable="false" checked="false" clickable="false" enabled="true" focusable="false" focused="false" long-clickable="false" password="false" scrollable="false" selected="false" bounds="[82,122][486,408]" displayed="true">
                                                                                          <android.view.View index="0" package="com.udates" class="android.view.View" text="My Chats" checkable="false" checked="false" clickable="false" enabled="true" focusable="false" focused="false" long-clickable="false" password="false" scrollable="false" selected="false" bounds="[82,208][486,322]" displayed="true" />
                                                                                        </android.view.ViewGroup>
                                                                                        <android.view.ViewGroup index="2" package="com.udates" class="android.view.ViewGroup" text="" checkable="false" checked="false" clickable="false" enabled="true" focusable="false" focused="false" long-clickable="false" password="false" scrollable="false" selected="false" bounds="[567,122][2160,408]" displayed="true">
                                                                                          <android.view.ViewGroup index="0" package="com.udates" class="android.view.ViewGroup" text="" checkable="false" checked="false" clickable="false" enabled="true" focusable="false" focused="false" long-clickable="false" password="false" scrollable="false" selected="false" bounds="[1905,153][2129,377]" displayed="true">
                                                                                            <android.view.ViewGroup index="0" package="com.udates" class="android.view.ViewGroup" text="" content-desc="Image Button" checkable="false" checked="false" clickable="true" enabled="true" focusable="true" focused="false" long-clickable="false" password="false" scrollable="false" selected="false" bounds="[1905,153][2129,377]" displayed="true">
                                                                                              <android.widget.ImageView index="0" package="com.udates" class="android.widget.ImageView" text="" checkable="false" checked="false" clickable="false" enabled="true" focusable="false" focused="false" long-clickable="false" password="false" scrollable="false" selected="false" bounds="[1956,204][2078,326]" displayed="true" />
                                                                                            </android.view.ViewGroup>
                                                                                          </android.view.ViewGroup>
                                                                                        </android.view.ViewGroup>
                                                                                      </android.view.ViewGroup>
                                                                                    </android.view.ViewGroup>
                                                                                  </android.view.ViewGroup>
                                                                                </android.view.ViewGroup>
                                                                                <android.view.ViewGroup index="1" package="com.udates" class="android.view.ViewGroup" text="" checkable="false" checked="false" clickable="false" enabled="true" focusable="false" focused="false" long-clickable="false" password="false" scrollable="false" selected="false" bounds="[0,408][2160,3590]" displayed="true">
                                                                                  <android.view.ViewGroup index="0" package="com.udates" class="android.view.ViewGroup" text="" checkable="false" checked="false" clickable="false" enabled="true" focusable="false" focused="false" long-clickable="false" password="false" scrollable="false" selected="false" bounds="[0,408][2160,3590]" displayed="true">
                                                                                    <android.view.ViewGroup index="0" package="com.udates" class="android.view.ViewGroup" text="" checkable="false" checked="false" clickable="false" enabled="true" focusable="false" focused="false" long-clickable="false" password="false" scrollable="false" selected="false" bounds="[0,408][2160,3590]" displayed="true">
                                                                                      <android.view.ViewGroup index="0" package="com.udates" class="android.view.ViewGroup" text="" checkable="false" checked="false" clickable="false" enabled="true" focusable="false" focused="false" long-clickable="false" password="false" scrollable="false" selected="false" bounds="[0,408][2160,499]" displayed="true" />
                                                                                      <android.view.ViewGroup index="1" package="com.udates" class="android.view.ViewGroup" text="" checkable="false" checked="false" clickable="false" enabled="true" focusable="false" focused="false" long-clickable="false" password="false" scrollable="false" selected="false" bounds="[0,500][2160,3590]" displayed="true">
                                                                                        <android.widget.ScrollView index="0" package="com.udates" class="android.widget.ScrollView" text="" content-desc="Chats list" checkable="false" checked="false" clickable="false" enabled="true" focusable="true" focused="false" long-clickable="false" password="false" scrollable="true" selected="false" bounds="[0,500][2160,3590]" displayed="true">
                                                                                          <android.view.ViewGroup index="0" package="com.udates" class="android.view.ViewGroup" text="" checkable="false" checked="false" clickable="false" enabled="true" focusable="false" focused="false" long-clickable="false" password="false" scrollable="false" selected="false" bounds="[0,500][2160,1969]" displayed="true">
                                                                                            <android.view.ViewGroup index="0" package="com.udates" class="android.view.ViewGroup" text="" checkable="false" checked="false" clickable="false" enabled="true" focusable="false" focused="false" long-clickable="false" password="false" scrollable="false" selected="false" bounds="[0,500][2160,990]" displayed="true">
                                                                                              <android.view.ViewGroup index="0" package="com.udates" class="android.view.ViewGroup" text="" checkable="false" checked="false" clickable="false" enabled="true" focusable="false" focused="false" long-clickable="false" password="false" scrollable="false" selected="false" bounds="[0,500][2160,990]" displayed="true">
                                                                                                <android.view.ViewGroup index="0" package="com.udates" class="android.view.ViewGroup" text="" checkable="false" checked="false" clickable="false" enabled="true" focusable="false" focused="false" long-clickable="false" password="false" scrollable="false" selected="false" bounds="[0,500][2160,990]" displayed="true">
                                                                                                  <android.view.ViewGroup index="0" package="com.udates" class="android.view.ViewGroup" text="" checkable="false" checked="false" clickable="true" enabled="true" focusable="true" focused="false" long-clickable="false" password="false" scrollable="false" selected="false" bounds="[0,500][2160,990]" displayed="true">
                                                                                                    <android.view.ViewGroup index="0" package="com.udates" class="android.view.ViewGroup" text="" content-desc="Chat Item 67910602231" checkable="false" checked="false" clickable="true" enabled="true" focusable="true" focused="false" long-clickable="false" password="false" scrollable="false" selected="false" bounds="[0,500][2160,990]" displayed="true">
                                                                                                      <android.view.ViewGroup index="0" package="com.udates" class="android.view.ViewGroup" text="" checkable="false" checked="false" clickable="false" enabled="true" focusable="false" focused="false" long-clickable="false" password="false" scrollable="false" selected="false" bounds="[0,500][2160,990]" displayed="true">
                                                                                                        <android.view.ViewGroup index="0" package="com.udates" class="android.view.ViewGroup" text="" checkable="false" checked="false" clickable="false" enabled="true" focusable="false" focused="false" long-clickable="false" password="false" scrollable="false" selected="false" bounds="[0,500][2160,990]" displayed="true">
                                                                                                          <android.view.ViewGroup index="0" package="com.udates" class="android.view.ViewGroup" text="" checkable="false" checked="false" clickable="false" enabled="true" focusable="false" focused="false" long-clickable="false" password="false" scrollable="false" selected="false" bounds="[82,538][495,951]" displayed="true">
                                                                                                            <android.view.ViewGroup index="0" package="com.udates" class="android.view.ViewGroup" text="" content-desc="chat container 67910602231" checkable="false" checked="false" clickable="false" enabled="true" focusable="false" focused="false" long-clickable="false" password="false" scrollable="false" selected="false" bounds="[82,538][495,951]" displayed="true">
                                                                                                              <android.view.ViewGroup index="0" package="com.udates" class="android.view.ViewGroup" text="" content-desc="expiring indicator container" checkable="false" checked="false" clickable="false" enabled="true" focusable="false" focused="false" long-clickable="false" password="false" scrollable="false" selected="false" bounds="[82,538][495,951]" displayed="true">
                                                                                                                <android.view.View index="0" package="com.udates" class="android.view.View" text="" checkable="false" checked="false" clickable="false" enabled="true" focusable="false" focused="false" long-clickable="false" password="false" scrollable="false" selected="false" bounds="[82,538][495,951]" displayed="true" />
                                                                                                              </android.view.ViewGroup>
                                                                                                              <android.view.ViewGroup index="1" package="com.udates" class="android.view.ViewGroup" text="" checkable="false" checked="false" clickable="false" enabled="true" focusable="false" focused="false" long-clickable="false" password="false" scrollable="false" selected="false" bounds="[95,551][483,939]" displayed="true">
                                                                                                                <android.widget.ImageView index="0" package="com.udates" class="android.widget.ImageView" text="" content-desc="User thumbnail" checkable="false" checked="false" clickable="false" enabled="true" focusable="false" focused="false" long-clickable="false" password="false" scrollable="false" selected="false" bounds="[115,571][462,918]" displayed="true" />
                                                                                                              </android.view.ViewGroup>
                                                                                                            </android.view.ViewGroup>
                                                                                                          </android.view.ViewGroup>
                                                                                                          <android.view.ViewGroup index="1" package="com.udates" class="android.view.ViewGroup" text="" checkable="false" checked="false" clickable="false" enabled="true" focusable="false" focused="false" long-clickable="false" password="false" scrollable="false" selected="false" bounds="[576,500][2160,990]" displayed="true">
                                                                                                            <android.view.ViewGroup index="0" package="com.udates" class="android.view.ViewGroup" text="" checkable="false" checked="false" clickable="false" enabled="true" focusable="false" focused="false" long-clickable="false" password="false" scrollable="false" selected="false" bounds="[576,646][2160,839]" displayed="true">
                                                                                                              <android.view.ViewGroup index="0" package="com.udates" class="android.view.ViewGroup" text="" checkable="false" checked="false" clickable="false" enabled="true" focusable="false" focused="false" long-clickable="false" password="false" scrollable="false" selected="false" bounds="[576,646][2078,739]" displayed="true">
                                                                                                                <android.view.ViewGroup index="0" package="com.udates" class="android.view.ViewGroup" text="" checkable="false" checked="false" clickable="false" enabled="true" focusable="false" focused="false" long-clickable="false" password="false" scrollable="false" selected="false" bounds="[576,646][1355,739]" displayed="true">
                                                                                                                  <android.widget.TextView index="0" package="com.udates" class="android.widget.TextView" text="Nancy wants to chat." content-desc="User name" checkable="false" checked="false" clickable="false" enabled="true" focusable="false" focused="false" long-clickable="false" password="false" scrollable="false" selected="false" bounds="[576,646][1304,739]" displayed="true" />
                                                                                                                </android.view.ViewGroup>
                                                                                                                <android.widget.TextView index="1" package="com.udates" class="android.widget.TextView" text="03:50 AM" content-desc="Message time" checkable="false" checked="false" clickable="false" enabled="true" focusable="false" focused="false" long-clickable="false" password="false" scrollable="false" selected="false" bounds="[1798,646][2078,707]" displayed="true" />
                                                                                                              </android.view.ViewGroup>
                                                                                                              <android.view.ViewGroup index="1" package="com.udates" class="android.view.ViewGroup" text="" checkable="false" checked="false" clickable="false" enabled="true" focusable="false" focused="false" long-clickable="false" password="false" scrollable="false" selected="false" bounds="[576,739][2160,839]" displayed="true">
                                                                                                                <android.view.ViewGroup index="0" package="com.udates" class="android.view.ViewGroup" text="" checkable="false" checked="false" clickable="false" enabled="true" focusable="false" focused="false" long-clickable="false" password="false" scrollable="false" selected="false" bounds="[576,739][2160,839]" displayed="true">
                                                                                                                  <android.widget.TextView index="0" package="com.udates" class="android.widget.TextView" text="Say Hello! 0" content-desc="Message text greeting" checkable="false" checked="false" clickable="false" enabled="true" focusable="false" focused="false" long-clickable="false" password="false" scrollable="false" selected="false" bounds="[576,739][2081,839]" displayed="true" />
                                                                                                                </android.view.ViewGroup>
                                                                                                              </android.view.ViewGroup>
                                                                                                            </android.view.ViewGroup>
                                                                                                          </android.view.ViewGroup>
                                                                                                        </android.view.ViewGroup>
                                                                                                      </android.view.ViewGroup>
                                                                                                    </android.view.ViewGroup>
                                                                                                  </android.view.ViewGroup>
                                                                                                </android.view.ViewGroup>
                                                                                                <android.view.ViewGroup index="1" package="com.udates" class="android.view.ViewGroup" text="" checkable="false" checked="false" clickable="false" enabled="true" focusable="false" focused="false" long-clickable="false" password="false" scrollable="false" selected="false" bounds="[0,500][2160,990]" displayed="true">
                                                                                                  <android.view.ViewGroup index="0" package="com.udates" class="android.view.ViewGroup" text="" checkable="false" checked="false" clickable="false" enabled="true" focusable="false" focused="false" long-clickable="false" password="false" scrollable="false" selected="false" bounds="[0,500][2160,990]" displayed="true">
                                                                                                    <android.view.ViewGroup index="0" package="com.udates" class="android.view.ViewGroup" text="" content-desc="Delete chat button 310679106022" checkable="false" checked="false" clickable="true" enabled="true" focusable="true" focused="false" long-clickable="false" password="false" scrollable="false" selected="false" bounds="[1670,500][2160,990]" displayed="true">
                                                                                                      <android.widget.TextView index="0" package="com.udates" class="android.widget.TextView" text="Delete" checkable="false" checked="false" clickable="false" enabled="true" focusable="false" focused="false" long-clickable="false" password="false" scrollable="false" selected="false" bounds="[1814,705][2015,785]" displayed="true" />
                                                                                                    </android.view.ViewGroup>
                                                                                                  </android.view.ViewGroup>
                                                                                                </android.view.ViewGroup>
                                                                                              </android.view.ViewGroup>
                                                                                            </android.view.ViewGroup>
                                                                                            <android.view.ViewGroup index="1" package="com.udates" class="android.view.ViewGroup" text="" checkable="false" checked="false" clickable="false" enabled="true" focusable="false" focused="false" long-clickable="false" password="false" scrollable="false" selected="false" bounds="[0,990][2160,1480]" displayed="true">
                                                                                              <android.view.ViewGroup index="0" package="com.udates" class="android.view.ViewGroup" text="" checkable="false" checked="false" clickable="false" enabled="true" focusable="false" focused="false" long-clickable="false" password="false" scrollable="false" selected="false" bounds="[0,990][2160,1480]" displayed="true">
                                                                                                <android.view.ViewGroup index="0" package="com.udates" class="android.view.ViewGroup" text="" checkable="false" checked="false" clickable="false" enabled="true" focusable="false" focused="false" long-clickable="false" password="false" scrollable="false" selected="false" bounds="[0,990][2160,1480]" displayed="true">
                                                                                                  <android.view.ViewGroup index="0" package="com.udates" class="android.view.ViewGroup" text="" checkable="false" checked="false" clickable="true" enabled="true" focusable="true" focused="false" long-clickable="false" password="false" scrollable="false" selected="false" bounds="[0,990][2160,1480]" displayed="true">
                                                                                                    <android.view.ViewGroup index="0" package="com.udates" class="android.view.ViewGroup" text="" content-desc="Chat Item 20736783742" checkable="false" checked="false" clickable="true" enabled="true" focusable="true" focused="false" long-clickable="false" password="false" scrollable="false" selected="false" bounds="[0,990][2160,1480]" displayed="true">
                                                                                                      <android.view.ViewGroup index="0" package="com.udates" class="android.view.ViewGroup" text="" checkable="false" checked="false" clickable="false" enabled="true" focusable="false" focused="false" long-clickable="false" password="false" scrollable="false" selected="false" bounds="[0,990][2160,1480]" displayed="true">
                                                                                                        <android.view.ViewGroup index="0" package="com.udates" class="android.view.ViewGroup" text="" checkable="false" checked="false" clickable="false" enabled="true" focusable="false" focused="false" long-clickable="false" password="false" scrollable="false" selected="false" bounds="[0,990][2160,1480]" displayed="true">
                                                                                                          <android.view.ViewGroup index="0" package="com.udates" class="android.view.ViewGroup" text="" checkable="false" checked="false" clickable="false" enabled="true" focusable="false" focused="false" long-clickable="false" password="false" scrollable="false" selected="false" bounds="[82,1028][495,1441]" displayed="true">
                                                                                                            <android.view.ViewGroup index="0" package="com.udates" class="android.view.ViewGroup" text="" content-desc="chat container 20736783742" checkable="false" checked="false" clickable="false" enabled="true" focusable="false" focused="false" long-clickable="false" password="false" scrollable="false" selected="false" bounds="[82,1028][495,1441]" displayed="true">
                                                                                                              <android.view.ViewGroup index="0" package="com.udates" class="android.view.ViewGroup" text="" content-desc="expiring indicator container" checkable="false" checked="false" clickable="false" enabled="true" focusable="false" focused="false" long-clickable="false" password="false" scrollable="false" selected="false" bounds="[82,1028][495,1441]" displayed="true">
                                                                                                                <android.view.View index="0" package="com.udates" class="android.view.View" text="" checkable="false" checked="false" clickable="false" enabled="true" focusable="false" focused="false" long-clickable="false" password="false" scrollable="false" selected="false" bounds="[82,1028][495,1441]" displayed="true" />
                                                                                                              </android.view.ViewGroup>
                                                                                                              <android.view.ViewGroup index="1" package="com.udates" class="android.view.ViewGroup" text="" checkable="false" checked="false" clickable="false" enabled="true" focusable="false" focused="false" long-clickable="false" password="false" scrollable="false" selected="false" bounds="[95,1041][483,1429]" displayed="true">
                                                                                                                <android.widget.ImageView index="0" package="com.udates" class="android.widget.ImageView" text="" content-desc="User thumbnail" checkable="false" checked="false" clickable="false" enabled="true" focusable="false" focused="false" long-clickable="false" password="false" scrollable="false" selected="false" bounds="[115,1061][462,1408]" displayed="true" />
                                                                                                              </android.view.ViewGroup>
                                                                                                            </android.view.ViewGroup>
                                                                                                          </android.view.ViewGroup>
                                                                                                          <android.view.ViewGroup index="1" package="com.udates" class="android.view.ViewGroup" text="" checkable="false" checked="false" clickable="false" enabled="true" focusable="false" focused="false" long-clickable="false" password="false" scrollable="false" selected="false" bounds="[576,990][2160,1480]" displayed="true">
                                                                                                            <android.view.ViewGroup index="0" package="com.udates" class="android.view.ViewGroup" text="" checkable="false" checked="false" clickable="false" enabled="true" focusable="false" focused="false" long-clickable="false" password="false" scrollable="false" selected="false" bounds="[576,1135][2160,1330]" displayed="true">
                                                                                                              <android.view.ViewGroup index="0" package="com.udates" class="android.view.ViewGroup" text="" checkable="false" checked="false" clickable="false" enabled="true" focusable="false" focused="false" long-clickable="false" password="false" scrollable="false" selected="false" bounds="[576,1135][2078,1228]" displayed="true">
                                                                                                                <android.view.ViewGroup index="0" package="com.udates" class="android.view.ViewGroup" text="" checkable="false" checked="false" clickable="false" enabled="true" focusable="false" focused="false" long-clickable="false" password="false" scrollable="false" selected="false" bounds="[576,1135][971,1228]" displayed="true">
                                                                                                                  <android.widget.TextView index="0" package="com.udates" class="android.widget.TextView" text="Savannah" content-desc="User name" checkable="false" checked="false" clickable="false" enabled="true" focusable="false" focused="false" long-clickable="false" password="false" scrollable="false" selected="false" bounds="[576,1135][920,1228]" displayed="true" />
                                                                                                                </android.view.ViewGroup>
                                                                                                                <android.widget.TextView index="1" package="com.udates" class="android.widget.TextView" text="Dec 24" content-desc="Message time" checkable="false" checked="false" clickable="false" enabled="true" focusable="false" focused="false" long-clickable="false" password="false" scrollable="false" selected="false" bounds="[1867,1135][2078,1196]" displayed="true" />
                                                                                                              </android.view.ViewGroup>
                                                                                                              <android.view.ViewGroup index="1" package="com.udates" class="android.view.ViewGroup" text="" checkable="false" checked="false" clickable="false" enabled="true" focusable="false" focused="false" long-clickable="false" password="false" scrollable="false" selected="false" bounds="[576,1228][2160,1330]" displayed="true">
                                                                                                                <android.view.ViewGroup index="0" package="com.udates" class="android.view.ViewGroup" text="" checkable="false" checked="false" clickable="false" enabled="true" focusable="false" focused="false" long-clickable="false" password="false" scrollable="false" selected="false" bounds="[576,1228][2160,1330]" displayed="true">
                                                                                                                  <android.view.ViewGroup index="0" package="com.udates" class="android.view.ViewGroup" text="" checkable="false" checked="false" clickable="false" enabled="true" focusable="false" focused="false" long-clickable="false" password="false" scrollable="false" selected="false" bounds="[576,1238][2160,1330]" displayed="true">
                                                                                                                    <android.widget.TextView index="0" package="com.udates" class="android.widget.TextView" text="How long can you be angry with your lover?" content-desc="Message text" checkable="false" checked="false" clickable="false" enabled="true" focusable="false" focused="false" long-clickable="false" password="false" scrollable="false" selected="false" bounds="[576,1238][1900,1330]" displayed="true" />
                                                                                                                  </android.view.ViewGroup>
                                                                                                                </android.view.ViewGroup>
                                                                                                              </android.view.ViewGroup>
                                                                                                            </android.view.ViewGroup>
                                                                                                          </android.view.ViewGroup>
                                                                                                        </android.view.ViewGroup>
                                                                                                      </android.view.ViewGroup>
                                                                                                    </android.view.ViewGroup>
                                                                                                  </android.view.ViewGroup>
                                                                                                </android.view.ViewGroup>
                                                                                                <android.view.ViewGroup index="1" package="com.udates" class="android.view.ViewGroup" text="" checkable="false" checked="false" clickable="false" enabled="true" focusable="false" focused="false" long-clickable="false" password="false" scrollable="false" selected="false" bounds="[0,990][2160,1480]" displayed="true">
                                                                                                  <android.view.ViewGroup index="0" package="com.udates" class="android.view.ViewGroup" text="" checkable="false" checked="false" clickable="false" enabled="true" focusable="false" focused="false" long-clickable="false" password="false" scrollable="false" selected="false" bounds="[0,990][2160,1480]" displayed="true">
                                                                                                    <android.view.ViewGroup index="0" package="com.udates" class="android.view.ViewGroup" text="" content-desc="Delete chat button 420207367837" checkable="false" checked="false" clickable="true" enabled="true" focusable="true" focused="false" long-clickable="false" password="false" scrollable="false" selected="false" bounds="[1670,990][2160,1480]" displayed="true">
                                                                                                      <android.widget.TextView index="0" package="com.udates" class="android.widget.TextView" text="Delete" checkable="false" checked="false" clickable="false" enabled="true" focusable="false" focused="false" long-clickable="false" password="false" scrollable="false" selected="false" bounds="[1814,1195][2015,1275]" displayed="true" />
                                                                                                    </android.view.ViewGroup>
                                                                                                  </android.view.ViewGroup>
                                                                                                </android.view.ViewGroup>
                                                                                              </android.view.ViewGroup>
                                                                                            </android.view.ViewGroup>
                                                                                            <android.view.ViewGroup index="2" package="com.udates" class="android.view.ViewGroup" text="" checkable="false" checked="false" clickable="false" enabled="true" focusable="false" focused="false" long-clickable="false" password="false" scrollable="false" selected="false" bounds="[0,1479][2160,1968]" displayed="true">
                                                                                              <android.view.ViewGroup index="0" package="com.udates" class="android.view.ViewGroup" text="" checkable="false" checked="false" clickable="false" enabled="true" focusable="false" focused="false" long-clickable="false" password="false" scrollable="false" selected="false" bounds="[0,1479][2160,1968]" displayed="true">
                                                                                                <android.view.ViewGroup index="0" package="com.udates" class="android.view.ViewGroup" text="" checkable="false" checked="false" clickable="false" enabled="true" focusable="false" focused="false" long-clickable="false" password="false" scrollable="false" selected="false" bounds="[0,1479][2160,1968]" displayed="true">
                                                                                                  <android.view.ViewGroup index="0" package="com.udates" class="android.view.ViewGroup" text="" checkable="false" checked="false" clickable="true" enabled="true" focusable="true" focused="false" long-clickable="false" password="false" scrollable="false" selected="false" bounds="[0,1479][2160,1968]" displayed="true">
                                                                                                    <android.view.ViewGroup index="0" package="com.udates" class="android.view.ViewGroup" text="" content-desc="Chat Item 20734810742" checkable="false" checked="false" clickable="true" enabled="true" focusable="true" focused="false" long-clickable="false" password="false" scrollable="false" selected="false" bounds="[0,1479][2160,1968]" displayed="true">
                                                                                                      <android.view.ViewGroup index="0" package="com.udates" class="android.view.ViewGroup" text="" checkable="false" checked="false" clickable="false" enabled="true" focusable="false" focused="false" long-clickable="false" password="false" scrollable="false" selected="false" bounds="[0,1479][2160,1968]" displayed="true">
                                                                                                        <android.view.ViewGroup index="0" package="com.udates" class="android.view.ViewGroup" text="" checkable="false" checked="false" clickable="false" enabled="true" focusable="false" focused="false" long-clickable="false" password="false" scrollable="false" selected="false" bounds="[0,1479][2160,1968]" displayed="true">
                                                                                                          <android.view.ViewGroup index="0" package="com.udates" class="android.view.ViewGroup" text="" checkable="false" checked="false" clickable="false" enabled="true" focusable="false" focused="false" long-clickable="false" password="false" scrollable="false" selected="false" bounds="[82,1517][495,1930]" displayed="true">
                                                                                                            <android.view.ViewGroup index="0" package="com.udates" class="android.view.ViewGroup" text="" content-desc="chat container 20734810742" checkable="false" checked="false" clickable="false" enabled="true" focusable="false" focused="false" long-clickable="false" password="false" scrollable="false" selected="false" bounds="[82,1517][495,1930]" displayed="true">
                                                                                                              <android.view.ViewGroup index="0" package="com.udates" class="android.view.ViewGroup" text="" content-desc="expiring indicator container" checkable="false" checked="false" clickable="false" enabled="true" focusable="false" focused="false" long-clickable="false" password="false" scrollable="false" selected="false" bounds="[82,1517][495,1930]" displayed="true">
                                                                                                                <android.view.View index="0" package="com.udates" class="android.view.View" text="" checkable="false" checked="false" clickable="false" enabled="true" focusable="false" focused="false" long-clickable="false" password="false" scrollable="false" selected="false" bounds="[82,1517][495,1930]" displayed="true" />
                                                                                                              </android.view.ViewGroup>
                                                                                                              <android.view.ViewGroup index="1" package="com.udates" class="android.view.ViewGroup" text="" checkable="false" checked="false" clickable="false" enabled="true" focusable="false" focused="false" long-clickable="false" password="false" scrollable="false" selected="false" bounds="[95,1530][483,1917]" displayed="true">
                                                                                                                <android.widget.ImageView index="0" package="com.udates" class="android.widget.ImageView" text="" content-desc="User thumbnail" checkable="false" checked="false" clickable="false" enabled="true" focusable="false" focused="false" long-clickable="false" password="false" scrollable="false" selected="false" bounds="[115,1550][462,1897]" displayed="true" />
                                                                                                              </android.view.ViewGroup>
                                                                                                            </android.view.ViewGroup>
                                                                                                          </android.view.ViewGroup>
                                                                                                          <android.view.ViewGroup index="1" package="com.udates" class="android.view.ViewGroup" text="" checkable="false" checked="false" clickable="false" enabled="true" focusable="false" focused="false" long-clickable="false" password="false" scrollable="false" selected="false" bounds="[576,1479][2160,1968]" displayed="true">
                                                                                                            <android.view.ViewGroup index="0" package="com.udates" class="android.view.ViewGroup" text="" checkable="false" checked="false" clickable="false" enabled="true" focusable="false" focused="false" long-clickable="false" password="false" scrollable="false" selected="false" bounds="[576,1619][2160,1824]" displayed="true">
                                                                                                              <android.view.ViewGroup index="0" package="com.udates" class="android.view.ViewGroup" text="" checkable="false" checked="false" clickable="false" enabled="true" focusable="false" focused="false" long-clickable="false" password="false" scrollable="false" selected="false" bounds="[576,1619][2078,1712]" displayed="true">
                                                                                                                <android.view.ViewGroup index="0" package="com.udates" class="android.view.ViewGroup" text="" checkable="false" checked="false" clickable="false" enabled="true" focusable="false" focused="false" long-clickable="false" password="false" scrollable="false" selected="false" bounds="[576,1619][812,1712]" displayed="true">
                                                                                                                  <android.widget.TextView index="0" package="com.udates" class="android.widget.TextView" text="Anna" content-desc="User name" checkable="false" checked="false" clickable="false" enabled="true" focusable="false" focused="false" long-clickable="false" password="false" scrollable="false" selected="false" bounds="[576,1619][761,1712]" displayed="true" />
                                                                                                                </android.view.ViewGroup>
                                                                                                                <android.widget.TextView index="1" package="com.udates" class="android.widget.TextView" text="Dec 24" content-desc="Message time" checkable="false" checked="false" clickable="false" enabled="true" focusable="false" focused="false" long-clickable="false" password="false" scrollable="false" selected="false" bounds="[1867,1619][2078,1680]" displayed="true" />
                                                                                                              </android.view.ViewGroup>
                                                                                                              <android.view.ViewGroup index="1" package="com.udates" class="android.view.ViewGroup" text="" checkable="false" checked="false" clickable="false" enabled="true" focusable="false" focused="false" long-clickable="false" password="false" scrollable="false" selected="false" bounds="[576,1712][2160,1824]" displayed="true">
                                                                                                                <android.view.ViewGroup index="0" package="com.udates" class="android.view.ViewGroup" text="" checkable="false" checked="false" clickable="false" enabled="true" focusable="false" focused="false" long-clickable="false" password="false" scrollable="false" selected="false" bounds="[576,1722][1966,1815]" displayed="true">
                                                                                                                  <android.widget.TextView index="0" package="com.udates" class="android.widget.TextView" text="Its a Perfect Match!" content-desc="Message text perfect match" checkable="false" checked="false" clickable="false" enabled="true" focusable="false" focused="false" long-clickable="false" password="false" scrollable="false" selected="false" bounds="[576,1722][1897,1815]" displayed="true" />
                                                                                                                </android.view.ViewGroup>
                                                                                                                <android.widget.ImageView index="1" package="com.udates" class="android.widget.ImageView" text="" content-desc="Message match icon" checkable="false" checked="false" clickable="false" enabled="true" focusable="false" focused="false" long-clickable="false" password="false" scrollable="false" selected="false" bounds="[1966,1738][2078,1824]" displayed="true" />
                                                                                                              </android.view.ViewGroup>
                                                                                                            </android.view.ViewGroup>
                                                                                                          </android.view.ViewGroup>
                                                                                                        </android.view.ViewGroup>
                                                                                                      </android.view.ViewGroup>
                                                                                                    </android.view.ViewGroup>
                                                                                                  </android.view.ViewGroup>
                                                                                                </android.view.ViewGroup>
                                                                                                <android.view.ViewGroup index="1" package="com.udates" class="android.view.ViewGroup" text="" checkable="false" checked="false" clickable="false" enabled="true" focusable="false" focused="false" long-clickable="false" password="false" scrollable="false" selected="false" bounds="[0,1479][2160,1968]" displayed="true">
                                                                                                  <android.view.ViewGroup index="0" package="com.udates" class="android.view.ViewGroup" text="" checkable="false" checked="false" clickable="false" enabled="true" focusable="false" focused="false" long-clickable="false" password="false" scrollable="false" selected="false" bounds="[0,1479][2160,1968]" displayed="true">
                                                                                                    <android.view.ViewGroup index="0" package="com.udates" class="android.view.ViewGroup" text="" content-desc="Delete chat button undefined" checkable="false" checked="false" clickable="true" enabled="true" focusable="true" focused="false" long-clickable="false" password="false" scrollable="false" selected="false" bounds="[1670,1479][2160,1968]" displayed="true">
                                                                                                      <android.widget.TextView index="0" package="com.udates" class="android.widget.TextView" text="Delete" checkable="false" checked="false" clickable="false" enabled="true" focusable="false" focused="false" long-clickable="false" password="false" scrollable="false" selected="false" bounds="[1814,1684][2015,1764]" displayed="true" />
                                                                                                    </android.view.ViewGroup>
                                                                                                  </android.view.ViewGroup>
                                                                                                </android.view.ViewGroup>
                                                                                              </android.view.ViewGroup>
                                                                                            </android.view.ViewGroup>
                                                                                          </android.view.ViewGroup>
                                                                                        </android.widget.ScrollView>
                                                                                      </android.view.ViewGroup>
                                                                                    </android.view.ViewGroup>
                                                                                  </android.view.ViewGroup>
                                                                                </android.view.ViewGroup>
                                                                              </android.view.ViewGroup>
                                                                            </android.view.ViewGroup>
                                                                          </android.view.ViewGroup>
                                                                        </android.view.ViewGroup>
                                                                      </android.view.ViewGroup>
                                                                    </android.view.ViewGroup>
                                                                  </android.widget.FrameLayout>
                                                                </android.view.ViewGroup>
                                                                <android.view.ViewGroup index="1" package="com.udates" class="android.view.ViewGroup" text="" checkable="false" checked="false" clickable="false" enabled="true" focusable="false" focused="false" long-clickable="false" password="false" scrollable="false" selected="false" bounds="[0,122][2160,408]" displayed="true" />
                                                              </android.view.ViewGroup>
                                                            </android.view.ViewGroup>
                                                          </android.view.ViewGroup>
                                                        </android.view.ViewGroup>
                                                      </android.view.ViewGroup>
                                                    </android.view.ViewGroup>
                                                  </android.view.ViewGroup>
                                                  <android.view.ViewGroup index="1" package="com.udates" class="android.view.ViewGroup" text="" checkable="false" checked="false" clickable="false" enabled="true" focusable="false" focused="false" long-clickable="false" password="false" scrollable="false" selected="false" bounds="[0,122][2160,3590]" displayed="true" />
                                                  <android.view.ViewGroup index="2" package="com.udates" class="android.view.ViewGroup" text="" checkable="false" checked="false" clickable="false" enabled="true" focusable="false" focused="false" long-clickable="false" password="false" scrollable="false" selected="false" bounds="[0,122][2160,3590]" displayed="true" />
                                                  <android.view.ViewGroup index="3" package="com.udates" class="android.view.ViewGroup" text="" checkable="false" checked="false" clickable="false" enabled="true" focusable="false" focused="false" long-clickable="false" password="false" scrollable="false" selected="false" bounds="[0,122][2160,3590]" displayed="true" />
                                                  <android.view.ViewGroup index="4" package="com.udates" class="android.view.ViewGroup" text="" checkable="false" checked="false" clickable="false" enabled="true" focusable="false" focused="false" long-clickable="false" password="false" scrollable="false" selected="false" bounds="[0,122][2160,3590]" displayed="true" />
                                                </android.view.ViewGroup>
                                                <android.view.ViewGroup index="1" package="com.udates" class="android.view.ViewGroup" text="" checkable="false" checked="false" clickable="false" enabled="true" focusable="false" focused="false" long-clickable="false" password="false" scrollable="false" selected="false" bounds="[0,3590][2160,3840]" displayed="true">
                                                  <android.view.ViewGroup index="0" package="com.udates" class="android.view.ViewGroup" text="" checkable="false" checked="false" clickable="false" enabled="true" focusable="false" focused="false" long-clickable="false" password="false" scrollable="false" selected="false" bounds="[0,3590][2160,3840]" displayed="true" />
                                                  <android.view.View index="1" package="com.udates" class="android.view.View" text="" checkable="false" checked="false" clickable="false" enabled="true" focusable="false" focused="false" long-clickable="false" password="false" scrollable="false" selected="false" bounds="[0,3590][2160,3840]" displayed="true">
                                                    <android.view.View index="0" package="com.udates" class="android.view.View" text="" resource-id="feed-screen-tab" checkable="false" checked="false" clickable="true" enabled="true" focusable="true" focused="false" long-clickable="false" password="false" scrollable="false" selected="false" bounds="[0,3590][432,3840]" displayed="true">
                                                      <android.widget.TextView index="1" package="com.udates" class="android.widget.TextView" text="Members" checkable="false" checked="false" clickable="false" enabled="true" focusable="false" focused="false" long-clickable="false" password="false" scrollable="false" selected="false" bounds="[110,3782][323,3840]" displayed="true" />
                                                    </android.view.View>
                                                    <android.view.View index="1" package="com.udates" class="android.view.View" text="" resource-id="live-screen-tab" checkable="false" checked="false" clickable="true" enabled="true" focusable="true" focused="false" long-clickable="false" password="false" scrollable="false" selected="false" bounds="[432,3590][864,3840]" displayed="true">
                                                      <android.widget.TextView index="1" package="com.udates" class="android.widget.TextView" text="Live" checkable="false" checked="false" clickable="false" enabled="true" focusable="false" focused="false" long-clickable="false" password="false" scrollable="false" selected="false" bounds="[604,3782][693,3840]" displayed="true" />
                                                    </android.view.View>
                                                    <android.view.View index="2" package="com.udates" class="android.view.View" text="" resource-id="chats-screen-tab" checkable="false" checked="false" clickable="true" enabled="true" focusable="true" focused="false" long-clickable="false" password="false" scrollable="false" selected="true" bounds="[864,3590][1296,3840]" displayed="true">
                                                      <android.widget.TextView index="1" package="com.udates" class="android.widget.TextView" text="Chats" checkable="false" checked="false" clickable="false" enabled="true" focusable="false" focused="false" long-clickable="false" password="false" scrollable="false" selected="true" bounds="[1016,3782][1144,3840]" displayed="true" />
                                                    </android.view.View>
                                                    <android.view.View index="3" package="com.udates" class="android.view.View" text="" resource-id="activity-screen-tab" checkable="false" checked="false" clickable="true" enabled="true" focusable="true" focused="false" long-clickable="false" password="false" scrollable="false" selected="false" bounds="[1296,3590][1728,3840]" displayed="true">
                                                      <android.widget.TextView index="1" package="com.udates" class="android.widget.TextView" text="Activity" checkable="false" checked="false" clickable="false" enabled="true" focusable="false" focused="false" long-clickable="false" password="false" scrollable="false" selected="false" bounds="[1430,3782][1595,3840]" displayed="true" />
                                                    </android.view.View>
                                                    <android.view.View index="4" package="com.udates" class="android.view.View" text="" resource-id="account-screen-tab" checkable="false" checked="false" clickable="true" enabled="true" focusable="true" focused="false" long-clickable="false" password="false" scrollable="false" selected="false" bounds="[1728,3590][2160,3840]" displayed="true">
                                                      <android.widget.TextView index="1" package="com.udates" class="android.widget.TextView" text="Me" checkable="false" checked="false" clickable="false" enabled="true" focusable="false" focused="false" long-clickable="false" password="false" scrollable="false" selected="false" bounds="[1910,3782][1979,3840]" displayed="true" />
                                                    </android.view.View>
                                                  </android.view.View>
                                                </android.view.ViewGroup>
                                              </android.view.ViewGroup>
                                            </android.view.ViewGroup>
                                          </android.view.ViewGroup>
                                        </android.view.ViewGroup>
                                      </android.view.ViewGroup>
                                    </android.view.ViewGroup>
                                  </android.view.ViewGroup>
                                </android.view.ViewGroup>
                              </android.widget.FrameLayout>
                            </android.view.ViewGroup>
                            <android.view.ViewGroup index="1" package="com.udates" class="android.view.ViewGroup" text="" checkable="false" checked="false" clickable="false" enabled="true" focusable="false" focused="false" long-clickable="false" password="false" scrollable="false" selected="false" bounds="[0,122][2160,408]" displayed="true" />
                          </android.view.ViewGroup>
                        </android.view.ViewGroup>
                      </android.view.ViewGroup>
                    </android.view.ViewGroup>
                  </android.view.ViewGroup>
                </android.view.ViewGroup>
              </android.view.ViewGroup>
            </android.widget.FrameLayout>
          </android.widget.FrameLayout>
        </android.widget.LinearLayout>
      </android.widget.FrameLayout>
    </android.widget.LinearLayout>
  </android.widget.FrameLayout>
</hierarchy>